{
    "dataset": "gdrive/MyDrive/Colab Notebooks/paper/00- My Data/Datasets/Direct Method/camel/camel_DE/camel_DE - v.02.csv",
    "preprocessing_params": {
        "columns_name": [
            "text",
            "bug_class_2"
        ],
        "columns_dtype": {
            "0": "str",
            "1": "int64"
        },
        "bug_classes": [
            0,
            1
        ],
        "num_bug_classes": 2,
        "keyword_Based": true,
        "docMaxLen": 100
    },
    "dataset_params": {
        "train_size": 0.8,
        "balance_train": true,
        "batch_size": 32
    },
    "model_params": {
        "filter_sizes": [
            3,
            4,
            5
        ],
        "conv_kernel_output_channel": 64,
        "embedding_size": 300,
        "longest_sentence_length": 17738,
        "dropout_zero_prob": 0.5
    },
    "train_params": {
        "epochs": 20,
        "l2_reg_lambda": 0.1,
        "max_learning_rate": 0.005,
        "min_learning_rate": 0.0001,
        "decay_coefficient": 2.5
    },
    "class_distributions": {
        "whole": {
            "0": 5863,
            "1": 3156
        },
        "train_balanced": {
            "0": 3562,
            "1": 3653
        },
        "train": {
            "0": 4674,
            "1": 2541
        },
        "validation": {
            "0": 1189,
            "1": 615
        }
    },
    "model_results": {
        "train": {
            "confusion_matrix": [
                [
                    [
                        3745,
                        929
                    ],
                    [
                        1909,
                        632
                    ]
                ],
                [
                    [
                        4203,
                        471
                    ],
                    [
                        1931,
                        610
                    ]
                ],
                [
                    [
                        4169,
                        505
                    ],
                    [
                        1571,
                        970
                    ]
                ],
                [
                    [
                        4236,
                        438
                    ],
                    [
                        1232,
                        1309
                    ]
                ],
                [
                    [
                        4274,
                        400
                    ],
                    [
                        1030,
                        1511
                    ]
                ],
                [
                    [
                        4314,
                        360
                    ],
                    [
                        830,
                        1711
                    ]
                ],
                [
                    [
                        4393,
                        281
                    ],
                    [
                        715,
                        1826
                    ]
                ],
                [
                    [
                        4418,
                        256
                    ],
                    [
                        640,
                        1901
                    ]
                ],
                [
                    [
                        4424,
                        250
                    ],
                    [
                        544,
                        1997
                    ]
                ],
                [
                    [
                        4454,
                        220
                    ],
                    [
                        514,
                        2027
                    ]
                ],
                [
                    [
                        4460,
                        214
                    ],
                    [
                        525,
                        2016
                    ]
                ],
                [
                    [
                        4468,
                        206
                    ],
                    [
                        475,
                        2066
                    ]
                ],
                [
                    [
                        4478,
                        196
                    ],
                    [
                        467,
                        2074
                    ]
                ],
                [
                    [
                        4476,
                        198
                    ],
                    [
                        445,
                        2096
                    ]
                ],
                [
                    [
                        4478,
                        196
                    ],
                    [
                        415,
                        2126
                    ]
                ],
                [
                    [
                        4491,
                        183
                    ],
                    [
                        423,
                        2118
                    ]
                ],
                [
                    [
                        4502,
                        172
                    ],
                    [
                        380,
                        2161
                    ]
                ],
                [
                    [
                        4512,
                        162
                    ],
                    [
                        377,
                        2164
                    ]
                ],
                [
                    [
                        4518,
                        156
                    ],
                    [
                        382,
                        2159
                    ]
                ],
                [
                    [
                        4512,
                        162
                    ],
                    [
                        361,
                        2180
                    ]
                ]
            ],
            "accuracy": [
                60.66528066528066,
                66.7082467082467,
                71.22661122661123,
                76.85377685377685,
                80.18018018018019,
                83.50658350658351,
                86.1954261954262,
                87.58142758142759,
                88.995148995149,
                89.82674982674983,
                89.75744975744976,
                90.56133056133056,
                90.81081081081082,
                91.08801108801109,
                91.53153153153153,
                91.6008316008316,
                92.34927234927235,
                92.52945252945253,
                92.54331254331254,
                92.75121275121275
            ],
            "acc_per_class": [
                [
                    80.12409071459136,
                    24.872097599370328
                ],
                [
                    89.9229781771502,
                    24.00629673356946
                ],
                [
                    89.19554985023535,
                    38.17394726485636
                ],
                [
                    90.62901155327343,
                    51.515151515151516
                ],
                [
                    91.44201968335473,
                    59.46477764659582
                ],
                [
                    92.29781771501926,
                    67.33569460842187
                ],
                [
                    93.9880188275567,
                    71.86147186147186
                ],
                [
                    94.52289259734702,
                    74.81306572215664
                ],
                [
                    94.65126230209671,
                    78.59110586383314
                ],
                [
                    95.29311082584509,
                    79.77174340810704
                ],
                [
                    95.42148053059478,
                    79.33884297520662
                ],
                [
                    95.59264013692768,
                    81.30657221566312
                ],
                [
                    95.80658964484383,
                    81.62140889413617
                ],
                [
                    95.76379974326059,
                    82.48720975993703
                ],
                [
                    95.80658964484383,
                    83.66784730421094
                ],
                [
                    96.08472400513479,
                    83.3530106257379
                ],
                [
                    96.32006846384253,
                    85.0452577725305
                ],
                [
                    96.53401797175867,
                    85.16332152695789
                ],
                [
                    96.66238767650835,
                    84.96654860291224
                ],
                [
                    96.53401797175867,
                    85.79299488390397
                ]
            ],
            "cost": [
                198.7847861647606,
                144.1283297240734,
                130.58557468652725,
                118.1841051876545,
                107.3828851878643,
                97.83314242959023,
                90.87307441234589,
                86.06021028757095,
                83.06328059732914,
                80.51777072250843,
                79.11063614487648,
                77.40883655846119,
                76.87063936889172,
                76.57116942107677,
                75.29093292355537,
                73.13945466279984,
                72.9277288466692,
                72.53773203492165,
                72.26119507849216,
                70.49496069550514
            ]
        },
        "validation": {
            "confusion_matrix": [
                [
                    [
                        1163,
                        26
                    ],
                    [
                        584,
                        31
                    ]
                ],
                [
                    [
                        1063,
                        126
                    ],
                    [
                        493,
                        122
                    ]
                ],
                [
                    [
                        1119,
                        70
                    ],
                    [
                        537,
                        78
                    ]
                ],
                [
                    [
                        1128,
                        61
                    ],
                    [
                        548,
                        67
                    ]
                ],
                [
                    [
                        1031,
                        158
                    ],
                    [
                        479,
                        136
                    ]
                ],
                [
                    [
                        1015,
                        174
                    ],
                    [
                        480,
                        135
                    ]
                ],
                [
                    [
                        1063,
                        126
                    ],
                    [
                        505,
                        110
                    ]
                ],
                [
                    [
                        1062,
                        127
                    ],
                    [
                        501,
                        114
                    ]
                ],
                [
                    [
                        1059,
                        130
                    ],
                    [
                        499,
                        116
                    ]
                ],
                [
                    [
                        1059,
                        130
                    ],
                    [
                        499,
                        116
                    ]
                ],
                [
                    [
                        978,
                        211
                    ],
                    [
                        443,
                        172
                    ]
                ],
                [
                    [
                        1031,
                        158
                    ],
                    [
                        481,
                        134
                    ]
                ],
                [
                    [
                        1015,
                        174
                    ],
                    [
                        478,
                        137
                    ]
                ],
                [
                    [
                        1019,
                        170
                    ],
                    [
                        476,
                        139
                    ]
                ],
                [
                    [
                        1016,
                        173
                    ],
                    [
                        475,
                        140
                    ]
                ],
                [
                    [
                        1007,
                        182
                    ],
                    [
                        469,
                        146
                    ]
                ],
                [
                    [
                        1043,
                        146
                    ],
                    [
                        494,
                        121
                    ]
                ],
                [
                    [
                        1020,
                        169
                    ],
                    [
                        478,
                        137
                    ]
                ],
                [
                    [
                        1000,
                        189
                    ],
                    [
                        465,
                        150
                    ]
                ],
                [
                    [
                        997,
                        192
                    ],
                    [
                        460,
                        155
                    ]
                ]
            ],
            "accuracy": [
                66.18625277161863,
                65.68736141906874,
                66.35254988913526,
                66.24168514412418,
                64.68957871396896,
                63.74722838137472,
                65.02217294900223,
                65.18847006651885,
                65.13303769401331,
                65.13303769401331,
                63.74722838137472,
                64.57871396895787,
                63.8580931263858,
                64.19068736141908,
                64.07982261640798,
                63.91352549889135,
                64.52328159645234,
                64.13525498891353,
                63.74722838137472,
                63.8580931263858
            ],
            "best_acc": 66.35254988913526,
            "best_at_step": 3,
            "acc_per_class": [
                [
                    97.81328847771236,
                    5.040650406504065
                ],
                [
                    89.40285954583683,
                    19.83739837398374
                ],
                [
                    94.11269974768713,
                    12.682926829268293
                ],
                [
                    94.86963835155593,
                    10.894308943089431
                ],
                [
                    86.71152228763667,
                    22.11382113821138
                ],
                [
                    85.36585365853658,
                    21.951219512195124
                ],
                [
                    89.40285954583683,
                    17.88617886178862
                ],
                [
                    89.31875525651807,
                    18.536585365853657
                ],
                [
                    89.06644238856181,
                    18.86178861788618
                ],
                [
                    89.06644238856181,
                    18.86178861788618
                ],
                [
                    82.25399495374263,
                    27.967479674796746
                ],
                [
                    86.71152228763667,
                    21.788617886178862
                ],
                [
                    85.36585365853658,
                    22.276422764227643
                ],
                [
                    85.70227081581162,
                    22.601626016260163
                ],
                [
                    85.44995794785534,
                    22.76422764227642
                ],
                [
                    84.69301934398655,
                    23.739837398373982
                ],
                [
                    87.72077375946174,
                    19.67479674796748
                ],
                [
                    85.78637510513036,
                    22.276422764227643
                ],
                [
                    84.10428931875525,
                    24.390243902439025
                ],
                [
                    83.85197645079899,
                    25.203252032520325
                ]
            ],
            "cost": [
                35.990874856710434,
                35.80801463127136,
                35.63350269198418,
                35.935955464839935,
                35.884251087903976,
                36.49965488910675,
                36.73965486884117,
                37.06315755844116,
                37.04176080226898,
                37.26829320192337,
                36.982447415590286,
                37.20769754052162,
                37.243213295936584,
                37.388543516397476,
                37.13108938932419,
                37.215493738651276,
                37.57752040028572,
                37.63297462463379,
                37.55355575680733,
                37.44124099612236
            ]
        },
        "time_to_train": "3h:48m:36s"
    }
}